{
  "id": "d52a751e-c28c-4413-b69e-4fe2ed237c90",
  "data_criacao": "2025-10-25T01:54:35.297963",
  "cliente_nome": "João Silva",
  "cliente_endereco": "Rua das Flores, 123",
  "cliente_telefone": "(11) 99999-9999",
  "potencia_sistema": 66.105,
  "preco_final": 90448.39,
  "preco_venda": 1514.29,
  "cidade": "São Paulo",
  "vendedor_nome": "Representante Comercial",
  "vendedor_cargo": "Especialista em Energia Solar",
  "vendedor_telefone": "(11) 99999-9999",
  "vendedor_email": "contato@empresa.com",
  "data_proposta": "25/10/2025",
  "conta_atual_anual": 63000.0,
  "anos_payback": 0.0,
  "gasto_acumulado_payback": 0.0,
  "consumo_mensal_kwh": "7000",
  "tarifa_energia": 0.75,
  "economia_mensal_estimada": 4987.5,
  "quantidade_placas": 0,
  "potencia_placa_w": 0,
  "area_necessaria": 291.54,
  "irradiacao_media": 5.15,
  "geracao_media_mensal": 25.71,
  "creditos_anuais": 279782.3458755,
  "economia_total_25_anos": 4653.46,
  "payback_meses": 0.0,
  "custo_total_projeto": 1060.0,
  "custo_equipamentos": 0.0,
  "custo_instalacao": 0,
  "custo_homologacao": 1000,
  "custo_outros": 0,
  "margem_lucro": 27134.517,
  "comissao_vendedor": 5,
  "custo_ca_aterramento": 0,
  "custo_plaquinhas": 60,
  "custo_obra": 0.0
}